zenoml_text_classification/__init__.py
zenoml_text_classification/frontend/index.mjs
zenoml_text_classification-0.0.2.dist-info/WHEEL
zenoml_text_classification-0.0.2.dist-info/METADATA
zenoml_text_classification-0.0.2.dist-info/RECORD
