Metadata-Version: 2.1
Name: zenoml-text-classification
Version: 0.0.2
Summary: Text Classification for Zeno
Home-page: https://dig.cmu.edu/zeno/
License: MIT
Keywords: ml,testing
Author: Ángel Alexander Cabrera
Author-email: alex.cabrera@gmail.com
Requires-Python: >=3.8,<3.11
Classifier: License :: OSI Approved :: MIT License
Classifier: Programming Language :: Python :: 3
Classifier: Programming Language :: Python :: 3.10
Classifier: Programming Language :: Python :: 3.8
Classifier: Programming Language :: Python :: 3.9
Project-URL: Repository, https://github.com/cmudig/zeno
